tinyfetch/__init__.py
tinyfetch/cli.py
tinyfetch/core.py
tinyfetch/module.py
tinyfetch-0.0.8.dist-info/METADATA
tinyfetch-0.0.8.dist-info/WHEEL
tinyfetch-0.0.8.dist-info/entry_points.txt
tinyfetch-0.0.8.dist-info/licenses/LICENSE.txt
tinyfetch-0.0.8.dist-info/RECORD
